cloudmarker/__init__.py
cloudmarker/__main__.py
cloudmarker/baseconfig.py
cloudmarker/manager.py
cloudmarker/util.py
cloudmarker/workers.py
cloudmarker/alerts/__init__.py
cloudmarker/alerts/emailalert.py
cloudmarker/alerts/slackalert.py
cloudmarker/clouds/__init__.py
cloudmarker/clouds/azcloud.py
cloudmarker/clouds/azvm.py
cloudmarker/clouds/gcpcloud.py
cloudmarker/clouds/mockcloud.py
cloudmarker/events/__init__.py
cloudmarker/events/azvmdatadiskencryptionevent.py
cloudmarker/events/azvmosdiskencryptionevent.py
cloudmarker/events/firewallruleevent.py
cloudmarker/events/mockevent.py
cloudmarker/stores/__init__.py
cloudmarker/stores/esstore.py
cloudmarker/stores/filestore.py
cloudmarker/stores/mongodbstore.py
cloudmarker/stores/splunkhecstore.py
cloudmarker-0.1.0.dist-info/LICENSE.rst
cloudmarker-0.1.0.dist-info/METADATA
cloudmarker-0.1.0.dist-info/WHEEL
cloudmarker-0.1.0.dist-info/entry_points.txt
cloudmarker-0.1.0.dist-info/top_level.txt
cloudmarker-0.1.0.dist-info/RECORD
