Metadata-Version: 2.1
Name: cloudmarker
Version: 0.1.0
Summary: Cloudmarker - Cloud security monitoring framework.
Home-page: https://github.com/cloudmarker/cloudmarker
Author: Cloudmarker Authors and Contributors
Author-email: UNKNOWN
License: UNKNOWN
Keywords: cloud security monitoring framework
Platform: UNKNOWN
Classifier: Development Status :: 2 - Pre-Alpha
Classifier: Intended Audience :: Developers
Classifier: Intended Audience :: End Users/Desktop
Classifier: Intended Audience :: Information Technology
Classifier: Intended Audience :: System Administrators
Classifier: License :: OSI Approved :: MIT License
Classifier: Operating System :: OS Independent
Classifier: Programming Language :: Python :: 3
Classifier: Topic :: System :: Monitoring
Requires-Dist: adal (==1.2.1)
Requires-Dist: asn1crypto (==0.24.0)
Requires-Dist: azure-common (==1.1.20)
Requires-Dist: azure-mgmt-compute (==5.0.0)
Requires-Dist: azure-mgmt-network (==2.7.0)
Requires-Dist: azure-mgmt-resource (==2.1.0)
Requires-Dist: azure-mgmt-storage (==3.3.0)
Requires-Dist: cachetools (==3.1.0)
Requires-Dist: certifi (==2019.3.9)
Requires-Dist: cffi (==1.12.3)
Requires-Dist: chardet (==3.0.4)
Requires-Dist: cryptography (==2.6.1)
Requires-Dist: elasticsearch (==7.0.1)
Requires-Dist: google-api-python-client (==1.7.8)
Requires-Dist: google-auth (==1.6.3)
Requires-Dist: google-auth-httplib2 (==0.0.3)
Requires-Dist: httplib2 (==0.12.3)
Requires-Dist: idna (==2.8)
Requires-Dist: isodate (==0.6.0)
Requires-Dist: msrest (==0.6.6)
Requires-Dist: msrestazure (==0.6.0)
Requires-Dist: oauthlib (==3.0.1)
Requires-Dist: pyasn1 (==0.4.5)
Requires-Dist: pyasn1-modules (==0.2.5)
Requires-Dist: pycparser (==2.19)
Requires-Dist: PyJWT (==1.7.1)
Requires-Dist: pymongo (==3.8.0)
Requires-Dist: python-dateutil (==2.8.0)
Requires-Dist: PyYAML (==5.1)
Requires-Dist: requests (==2.21.0)
Requires-Dist: requests-oauthlib (==1.2.0)
Requires-Dist: rsa (==4.0)
Requires-Dist: schedule (==0.6.0)
Requires-Dist: six (==1.12.0)
Requires-Dist: slackclient (==1.3.1)
Requires-Dist: uritemplate (==3.0.0)
Requires-Dist: urllib3 (==1.24.3)
Requires-Dist: websocket-client (==0.54.0)
